{"adem_relations":[[{"coeff":1,"gen":"x","op":[2]}],[{"coeff":1,"gen":"x","op":[3]},{"coeff":1,"gen":"x","op":[2,1]}],[{"coeff":1,"gen":"x","op":[4]}],[{"coeff":1,"gen":"x","op":[14]},{"coeff":1,"gen":"y","op":[7]},{"coeff":1,"gen":"y","op":[6,1]}],[{"coeff":1,"gen":"y","op":[10]},{"coeff":1,"gen":"y","op":[7,3]},{"coeff":1,"gen":"y","op":[8,2]},{"coeff":1,"gen":"y","op":[9,1]},{"coeff":1,"gen":"y","op":[6,3,1]}]],"file_name":"j_mod_2","generic":false,"gens":{"x":0,"y":7},"name":"$j/2$","p":2,"type":"finitely presented module"}